{
  "blocked_trade_dates": [
    "2026-05-11"
  ],
  "positions": [
    {
      "allocated_cash": 3400.0,
      "alpaca_entry_client_order_id": "rev-20260520111903-ttwo-early",
      "alpaca_entry_order_id": "3e3c8dfc-2286-4e36-9ffb-4cf8435d27c4",
      "alpaca_exit_order_id": "8a309bc9-b19c-4144-9daf-a4e3261cc6c0",
      "asset_type": "option",
      "contract_symbol": "TTWO260717C00240000",
      "contracts": 2,
      "current_drop_pct": 0.75,
      "early_entry_score": 0.871,
      "entry_mode": "early",
      "entry_option_price": 17.0,
      "entry_slot": "early_entry_1115",
      "entry_spot": 236.35499572753906,
      "entry_timestamp": "2026-05-20T11:19:03.434065-04:00",
      "entry_trade_date": "2026-05-20",
      "execution_mode": "alpaca_paper_option",
      "exit_reason": "take_profit_day1_hit_at_scan",
      "exit_reference_price": 18.9,
      "expiry": "2026-07-17",
      "matched_signals": 35,
      "planned_stop": 15.3,
      "planned_tp_day1": 19.549999999999997,
      "planned_tp_day2": 19.549999999999997,
      "position_id": "TTWO_20260520T111903",
      "status": "exit_submitted",
      "strike": 240.0,
      "success_rate": 100.0,
      "ticker": "TTWO",
      "timing_score": 0.428
    }
  ],
  "start_date": "2026-03-24",
  "version": "3.4.4-alpaca-paper.0"
}